pyut-reporter/__init__.py
pyut-reporter/html_report.py
pyut-reporter/render.py
pyut-reporter/templates/report.html
pyut_reporter-1.1.0.dist-info/licenses/LICENSE
tests/__init__.py
tests/test_nose_plugin.py
tests/test_template_render.py
pyut_reporter-1.1.0.dist-info/METADATA
pyut_reporter-1.1.0.dist-info/WHEEL
pyut_reporter-1.1.0.dist-info/top_level.txt
pyut_reporter-1.1.0.dist-info/RECORD
