Metadata-Version: 2.4
Name: pyut-reporter
Version: 1.1.0
Summary: This Library Generate a HTML and JSON report for your Nose Unit Tests
Home-page: https://github.com/pankajnayak1994/pyut-reporter
Download-URL: https://github.com/pankajnayak1994/pyut-reporter
Author: Pankaj Kumar Nayak
Author-email: nayakpankaj2015@gmail.com
License: MIT
Keywords: nose2,testing,reporting,pytest
Classifier: Development Status :: 3 - Alpha
Classifier: Intended Audience :: Developers
Classifier: Topic :: Software Development :: Testing
Classifier: License :: OSI Approved :: MIT License
Classifier: Programming Language :: Python :: 3.8
Classifier: Programming Language :: Python :: 3.9
Classifier: Programming Language :: Python :: 3.10
Classifier: Programming Language :: Python :: 3.11
Classifier: Programming Language :: Python :: 3.12
License-File: LICENSE
Requires-Dist: jinja2
Requires-Dist: nose2
Dynamic: author
Dynamic: author-email
Dynamic: classifier
Dynamic: description
Dynamic: description-content-type
Dynamic: download-url
Dynamic: home-page
Dynamic: keywords
Dynamic: license
Dynamic: license-file
Dynamic: requires-dist
Dynamic: summary
